{
  "date": "2026-05-13",
  "category": "trust",
  "article_count": 91,
  "source_count": 12,
  "matched_count": 91,
  "top_entities": [
    {
      "name": "SecurityGeneral",
      "count": 137
    },
    {
      "name": "Vulnerability",
      "count": 38
    },
    {
      "name": "Threat",
      "count": 36
    },
    {
      "name": "DataBreach",
      "count": 22
    },
    {
      "name": "Malware",
      "count": 15
    },
    {
      "name": "ConsumerTrust",
      "count": 12
    },
    {
      "name": "Privacy",
      "count": 10
    },
    {
      "name": "CorporateTrust",
      "count": 9
    },
    {
      "name": "Compliance",
      "count": 7
    }
  ],
  "sources": {
    "Bleeping Computer": 28,
    "Krebs on Security": 1,
    "Dark Reading": 6,
    "SANS Internet Storm Center": 2,
    "The Verge": 9,
    "TechCrunch": 12,
    "The Hacker News": 19,
    "Infosecurity Magazine": 8,
    "Schneier on Security": 3,
    "Securelist - Kaspersky": 1,
    "UK NCSC Blog": 1,
    "Troy Hunt - Have I Been Pwned": 1
  },
  "generated_at": "2026-05-13T08:48:30.576177+09:00"
}